leetifypy/__init__.py
leetifypy/scraper.py
leetifypy/utils.py
LeetifyPy-0.15.dist-info/METADATA
LeetifyPy-0.15.dist-info/WHEEL
LeetifyPy-0.15.dist-info/entry_points.txt
LeetifyPy-0.15.dist-info/top_level.txt
LeetifyPy-0.15.dist-info/RECORD
