Metadata-Version: 2.1
Name: LeetifyPy
Version: 0.15
Summary: A web scraping library using Selenium for Leetify to get player data.
Home-page: https://github.com/PhialsBasement/LeetifyPy
Author: Phial
Author-email: phialdial@example.com
License: MIT
Classifier: Programming Language :: Python :: 3
Classifier: License :: OSI Approved :: MIT License
Classifier: Operating System :: OS Independent
Requires-Dist: selenium
